nonebot_plugin_sideload/__init__.py
nonebot_plugin_sideload/config.py
nonebot_plugin_sideload/web/.last_build_id
nonebot_plugin_sideload/web/assets/AssetManifest.bin
nonebot_plugin_sideload/web/assets/AssetManifest.bin.json
nonebot_plugin_sideload/web/assets/AssetManifest.json
nonebot_plugin_sideload/web/assets/FontManifest.json
nonebot_plugin_sideload/web/assets/NOTICES
nonebot_plugin_sideload/web/assets/fonts/MaterialIcons-Regular.otf
nonebot_plugin_sideload/web/assets/lib/assets/logo.png
nonebot_plugin_sideload/web/assets/packages/cupertino_icons/assets/CupertinoIcons.ttf
nonebot_plugin_sideload/web/assets/shaders/ink_sparkle.frag
nonebot_plugin_sideload/web/canvaskit/canvaskit.js
nonebot_plugin_sideload/web/canvaskit/canvaskit.js.symbols
nonebot_plugin_sideload/web/canvaskit/canvaskit.wasm
nonebot_plugin_sideload/web/canvaskit/chromium/canvaskit.js
nonebot_plugin_sideload/web/canvaskit/chromium/canvaskit.js.symbols
nonebot_plugin_sideload/web/canvaskit/chromium/canvaskit.wasm
nonebot_plugin_sideload/web/canvaskit/skwasm.js
nonebot_plugin_sideload/web/canvaskit/skwasm.js.symbols
nonebot_plugin_sideload/web/canvaskit/skwasm.wasm
nonebot_plugin_sideload/web/canvaskit/skwasm.worker.js
nonebot_plugin_sideload/web/favicon.png
nonebot_plugin_sideload/web/flutter.js
nonebot_plugin_sideload/web/flutter_bootstrap.js
nonebot_plugin_sideload/web/icons/icon.png
nonebot_plugin_sideload/web/index.html
nonebot_plugin_sideload/web/main.dart.js
nonebot_plugin_sideload/web/manifest.json
nonebot_plugin_sideload/web/version.json
nonebot_plugin_sideload-0.1.8.dist-info/LICENSE
nonebot_plugin_sideload-0.1.8.dist-info/METADATA
nonebot_plugin_sideload-0.1.8.dist-info/WHEEL
nonebot_plugin_sideload-0.1.8.dist-info/RECORD
