Metadata-Version: 2.3
Name: nonebot-plugin-sideload
Version: 0.1.8
Summary: 为你的NoneBot侧载一个OneBot V11 Web聊天面板
License: GPL3
Author: 【夜风】NightWind
Author-email: 2125714976@qq.com
Requires-Python: >=3.9
Classifier: License :: Other/Proprietary License
Classifier: Programming Language :: Python :: 3
Classifier: Programming Language :: Python :: 3.9
Classifier: Programming Language :: Python :: 3.10
Classifier: Programming Language :: Python :: 3.11
Classifier: Programming Language :: Python :: 3.12
Classifier: Programming Language :: Python :: 3.13
Requires-Dist: aiosqlite (>=0.21.0)
Requires-Dist: httpx (>=0.22.0)
Requires-Dist: netifaces (>=0.11.0)
Requires-Dist: nonebot-adapter-onebot (>=2.4.5)
Requires-Dist: nonebot-plugin-localstore (>=0.7.3)
Requires-Dist: nonebot2 (>=2.4.0,<3.0.0)
Project-URL: Documentation, https://github.com/NonebotGUI/nonebot-plugin-sideload#README.md
Project-URL: Homepage, https://github.com/NonebotGUI/nonebot-plugin-sideload
Project-URL: Repository, https://github.com/NonebotGUI/nonebot-plugin-sideload
